LICENSE.txt
MANIFEST.in
README.rst
setup.cfg
setup.py
openet/__init__.py
openet/disalexi/__init__.py
openet/disalexi/disalexi.py
openet/disalexi/landsat.py
openet/disalexi/lc_properties.py
openet/disalexi/tseb.py
openet/disalexi/tseb_utils.py
openet/disalexi/utils.py
openet/disalexi/tests/__init__.py
openet/disalexi/tests/conftest.py
openet/disalexi/tests/idl_values.py
openet/disalexi/tests/test_disalexi.py
openet/disalexi/tests/test_landsat.py
openet/disalexi/tests/test_tseb.py
openet/disalexi/tests/test_tseb_utils.py
openet/disalexi/tests/test_utils.py
openet_disalexi.egg-info/PKG-INFO
openet_disalexi.egg-info/SOURCES.txt
openet_disalexi.egg-info/dependency_links.txt
openet_disalexi.egg-info/not-zip-safe
openet_disalexi.egg-info/requires.txt
openet_disalexi.egg-info/top_level.txt