Metadata-Version: 1.1
Name: openet-disalexi
Version: 0.0.1
Summary: Earth Engine based DisALEXI Model
Home-page: https://github.com/Open-ET/openet-disalexi-beta
Author: Charles Morton
Author-email: charles.morton@dri.edu
License: Apache
Download-URL: https://github.com/Open-ET/openet-disalexi-beta/archive/v0.0.1.tar.gz
Keywords: DisALEXI OpenET Evapotranspiration Earth Engine
Platform: UNKNOWN
Classifier: License :: OSI Approved :: Apache Software License
Classifier: Programming Language :: Python :: 3.6
